_test/__init__.py
_test/conftest.py
_test/core/__init__.py
_test/core/test_hook_function.py
_test/core/test_hook_function_group_manager.py
_test/core/test_wrapper.py
_test/distributed/__init__.py
_test/distributed/test_initialize.py
_test/multi_gpu/__init__.py
_test/multi_gpu/registry.py
_test/multi_gpu/run_multi_gpu_tests_slurm.py
_test/multi_gpu/testing_utils.py
_test/multi_gpu/core/__init__.py
_test/multi_gpu/core/test_dp_wrappers_vs_single_gpu.py
_test/multi_gpu/core/test_fairscale_mpu_vs_ddp.py
_test/multi_gpu/distributed/__init__.py
_test/multi_gpu/distributed/test_initialize.py
_test/multi_gpu/distributed/test_mappings.py
_test/traverse/__init__.py
_test/traverse/test_nodes.py
_test/traverse/test_ops.py
demos/__init__.py
demos/induction_heads_multigpu.py
examples/__init__.py
examples/fsdp_example.py
examples/megatron_example.py
examples/single_gpu_example.py
flex_model/__init__.py
flex_model/package_info.py
flex_model/utils.py
flex_model/core/__init__.py
flex_model/core/core_utils.py
flex_model/core/hook_function.py
flex_model/core/wrapper.py
flex_model/distributed/__init__.py
flex_model/distributed/distributed_state.py
flex_model/distributed/mappings.py
flex_model/distributed/strategies.py
flex_model/traverse/__init__.py
flex_model/traverse/nodes.py
flex_model/traverse/ops.py
profiling/__init__.py
profiling/profile_hooks.py
profiling/utils.py
flex_model-0.1.0.dist-info/LICENSE
flex_model-0.1.0.dist-info/METADATA
flex_model-0.1.0.dist-info/WHEEL
flex_model-0.1.0.dist-info/top_level.txt
flex_model-0.1.0.dist-info/RECORD
