Metadata-Version: 2.1
Name: flex-model
Version: 0.1.0
Summary: FlexModel - A Framework for Interpretability of Distributed Large Language Models
Home-page: https://github.com/VectorInstitute/flex_model
Author: Matthew Choi
Author-email: matthew.choi@vectorinstitute.ai
Maintainer: Matthew Choi
Maintainer-email: matthew.choi@vectorinstitute.ai
License: mit
License-File: LICENSE
Requires-Dist: torch >=2.1
Provides-Extra: all
Requires-Dist: torch >=2.1 ; extra == 'all'
Requires-Dist: fairscale ; extra == 'all'
Requires-Dist: pytest ; extra == 'all'
Requires-Dist: sentencepiece ; extra == 'all'
Requires-Dist: submitit ; extra == 'all'
Requires-Dist: tokenizers ; extra == 'all'
Requires-Dist: transformers ; extra == 'all'
Requires-Dist: coverage ; extra == 'all'
Requires-Dist: pre-commit ; extra == 'all'
Requires-Dist: ruff ; extra == 'all'
Requires-Dist: sphinx-rtd-theme ; extra == 'all'
Requires-Dist: matplotlib ; extra == 'all'
Provides-Extra: core
Requires-Dist: torch >=2.1 ; extra == 'core'
Provides-Extra: dev
Requires-Dist: torch >=2.1 ; extra == 'dev'
Requires-Dist: fairscale ; extra == 'dev'
Requires-Dist: pytest ; extra == 'dev'
Requires-Dist: sentencepiece ; extra == 'dev'
Requires-Dist: submitit ; extra == 'dev'
Requires-Dist: tokenizers ; extra == 'dev'
Requires-Dist: transformers ; extra == 'dev'
Requires-Dist: coverage ; extra == 'dev'
Requires-Dist: pre-commit ; extra == 'dev'
Requires-Dist: ruff ; extra == 'dev'
Requires-Dist: sphinx-rtd-theme ; extra == 'dev'
Provides-Extra: examples
Requires-Dist: torch >=2.1 ; extra == 'examples'
Requires-Dist: fairscale ; extra == 'examples'
Requires-Dist: sentencepiece ; extra == 'examples'
Requires-Dist: tokenizers ; extra == 'examples'
Requires-Dist: transformers ; extra == 'examples'
Requires-Dist: matplotlib ; extra == 'examples'
Provides-Extra: test
Requires-Dist: torch >=2.1 ; extra == 'test'
Requires-Dist: fairscale ; extra == 'test'
Requires-Dist: pytest ; extra == 'test'
Requires-Dist: sentencepiece ; extra == 'test'
Requires-Dist: submitit ; extra == 'test'
Requires-Dist: tokenizers ; extra == 'test'
Requires-Dist: transformers ; extra == 'test'
